tarefa3/tarefa3.vhd
library ieee;
use ieee.std_logic_1164.all;

entity tarefa3 is
  port ( A, B, C, D : in std_logic;
         s    : out std_logic );
end tarefa3;

architecture rtl of tarefa3 is
begin
    s <= (A and B)or(A and C)or(B and C and D); -- A B	+	A C	+	B C D
end rtl;

tarefa3/tarefa3_TB.vhd
library ieee;
use ieee.std_logic_1164.all;

entity tarefa3_TB is
end entity tarefa3_TB;

architecture sim of tarefa3_TB is
    signal A, B, C, D, s : std_logic;
begin
  DUT: entity work.tarefa3
    port map (A => A, B => B, C => C, D => D, s => s);

  stim: process
  begin
     A <= '0'; B <= '0'; C <= '0'; D <= '0'; wait for 10 ns;
     A <= '0'; B <= '1'; C <= '1'; D <= '1'; wait for 10 ns;
     A <= '0'; B <= '0'; C <= '1'; D <= '0'; wait for 10 ns;
     A <= '0'; B <= '0'; C <= '1'; D <= '1'; wait for 10 ns;
     A <= '1'; B <= '1'; C <= '0'; D <= '0'; wait for 10 ns;
     A <= '1'; B <= '0'; C <= '0'; D <= '1'; wait for 10 ns;
     A <= '1'; B <= '1'; C <= '1'; D <= '0'; wait for 10 ns;
     A <= '1'; B <= '1'; C <= '1'; D <= '1'; wait for 10 ns;
    wait;
  end process;
end architecture;

tarefa3/onda.vcd
$date
  Thu Sep 11 16:41:42 2025
$end
$version
  GHDL v0
$end
$timescale
  1 fs
$end
$scope module standard $end
$upscope $end
$scope module std_logic_1164 $end
$upscope $end
$scope module tarefa3_tb $end
$var reg 1 ! a $end
$var reg 1 " b $end
$var reg 1 # c $end
$var reg 1 $ d $end
$var reg 1 % s $end
$scope module dut $end
$var reg 1 & a $end
$var reg 1 ' b $end
$var reg 1 ( c $end
$var reg 1 ) d $end
$var reg 1 * s $end
$upscope $end
$upscope $end
$enddefinitions $end
#0
0!
0"
0#
0$
0%
0&
0'
0(
0)
0*
#10000000
1"
1#
1$
1%
1'
1(
1)
1*
#20000000
0"
0$
0%
0'
0)
0*
#30000000
1$
1)
#40000000
1!
1"
0#
0$
1%
1&
1'
0(
0)
1*
#50000000
0"
1$
0%
0'
1)
0*
#60000000
1"
1#
0$
1%
1'
1(
0)
1*
#70000000
1$
1)
