trefa5/flipflop_d.vhdl
library IEEE;
use IEEE.STD_LOGIC_1164.ALL;

entity flipflop_d is
    Port ( 
        D   : in  STD_LOGIC;  -- Entrada de dados
        CLK : in  STD_LOGIC;  -- Entrada de clock
        Q   : out STD_LOGIC;  -- Saída Q
        Q_n : out STD_LOGIC   -- Saída Q' (negada)
    );
end flipflop_d;

architecture Behavioral of flipflop_d is
    signal q_internal : STD_LOGIC := '0';
begin
    process(CLK)
    begin
        if rising_edge(CLK) then  -- Detecção de borda ascendente
            q_internal <= D;
        end if;
    end process;
    
    Q <= q_internal;      -- Saída Q
    Q_n <= not q_internal; -- Saída Q' (complemento)
end Behavioral;

trefa5/registrador_8bits.vhdl
library IEEE;
use IEEE.STD_LOGIC_1164.ALL;

entity registrador_8bits is
    Port ( 
        D   : in  STD_LOGIC_VECTOR(7 downto 0);  -- Entrada paralela de 8 bits
        CLK : in  STD_LOGIC;                     -- Clock comum
        Q   : out STD_LOGIC_VECTOR(7 downto 0);  -- Saída Q de 8 bits
        Q_n : out STD_LOGIC_VECTOR(7 downto 0)   -- Saída Q' de 8 bits
    );
end registrador_8bits;

architecture Structural of registrador_8bits is
begin
    -- Instantiate 8 D flip-flops using a generate loop and direct entity instantiation
    gen_ff: for i in 0 to 7 generate
        FF: entity work.flipflop_d port map (
            D   => D(i),
            CLK => CLK,
            Q   => Q(i),
            Q_n => Q_n(i)
        );
    end generate gen_ff;

end Structural;

trefa5/tb_registrador_8bits.vhd
library IEEE;
use IEEE.STD_LOGIC_1164.ALL;

entity tb_registrador_8bits is
end tb_registrador_8bits;

architecture Behavioral of tb_registrador_8bits is
    -- Declaração do componente a ser testado
    component registrador_8bits
        Port ( 
            D   : in  STD_LOGIC_VECTOR(7 downto 0);
            CLK : in  STD_LOGIC;
            Q   : out STD_LOGIC_VECTOR(7 downto 0);
            Q_n : out STD_LOGIC_VECTOR(7 downto 0)
        );
    end component;
    
    -- Sinais de teste
    signal D_test   : STD_LOGIC_VECTOR(7 downto 0) := (others => '0');
    signal CLK_test : STD_LOGIC := '0';
    signal Q_test   : STD_LOGIC_VECTOR(7 downto 0);
    signal Q_n_test : STD_LOGIC_VECTOR(7 downto 0);
    
    -- Período do clock
    constant CLK_PERIOD : time := 10 ns;
    -- Número de ciclos de clock para simular (ajuste para reduzir tamanho do VCD)
    constant NUM_CYCLES : natural := 16; 
    
begin
    -- Instanciação do registrador
    UUT: registrador_8bits port map (
        D   => D_test,
        CLK => CLK_test,
        Q   => Q_test,
        Q_n => Q_n_test
    );
    
    -- Clock de 10 ns
    clk_process: process
    begin
        for i in 0 to 20 loop
            CLK_test <= '0'; wait for 5 ns;
            CLK_test <= '1'; wait for 5 ns;
        end loop;
        wait; -- Para finalizar a simulação
    end process;

    -- Estímulos (os 8 valores solicitados)
    stim_process: process
    begin
        -- Teste 1: 00000000
        D_test <= "00000000"; wait for 10 ns;
        -- Teste 2: 11111111
        D_test <= "11111111"; wait for 10 ns;
        -- Teste 3: 10101010
        D_test <= "10101010"; wait for 10 ns;
        -- Teste 4: 01010101
        D_test <= "01010101"; wait for 10 ns;
        -- Teste 5: 11001100
        D_test <= "11001100"; wait for 10 ns;
        -- Teste 6: 00110011
        D_test <= "00110011"; wait for 10 ns;
        -- Teste 7: 11110000
        D_test <= "11110000"; wait for 10 ns;
        -- Teste 8: 00001111
        D_test <= "00001111"; wait for 10 ns;

        wait; -- Finaliza a simulação
    end process;
    
end Behavioral;

trefa5/tb_registrador_8bits.vcd
$date
  Fri Sep 19 08:14:09 2025
$end
$version
  GHDL v0
$end
$timescale
  1 fs
$end
$scope module standard $end
$upscope $end
$scope module std_logic_1164 $end
$upscope $end
$scope module tb_registrador_8bits $end
$var reg 8 ! d_test[7:0] $end
$var reg 1 " clk_test $end
$var reg 8 # q_test[7:0] $end
$var reg 8 $ q_n_test[7:0] $end
$scope module uut $end
$var reg 8 % d[7:0] $end
$var reg 1 & clk $end
$var reg 8 ' q[7:0] $end
$var reg 8 ( q_n[7:0] $end
$scope module gen_ff(0) $end
$scope module ff $end
$var reg 1 ) d $end
$var reg 1 * clk $end
$var reg 1 + q $end
$var reg 1 , q_n $end
$var reg 1 - q_internal $end
$upscope $end
$upscope $end
$scope module gen_ff(1) $end
$scope module ff $end
$var reg 1 . d $end
$var reg 1 / clk $end
$var reg 1 0 q $end
$var reg 1 1 q_n $end
$var reg 1 2 q_internal $end
$upscope $end
$upscope $end
$scope module gen_ff(2) $end
$scope module ff $end
$var reg 1 3 d $end
$var reg 1 4 clk $end
$var reg 1 5 q $end
$var reg 1 6 q_n $end
$var reg 1 7 q_internal $end
$upscope $end
$upscope $end
$scope module gen_ff(3) $end
$scope module ff $end
$var reg 1 8 d $end
$var reg 1 9 clk $end
$var reg 1 : q $end
$var reg 1 ; q_n $end
$var reg 1 < q_internal $end
$upscope $end
$upscope $end
$scope module gen_ff(4) $end
$scope module ff $end
$var reg 1 = d $end
$var reg 1 > clk $end
$var reg 1 ? q $end
$var reg 1 @ q_n $end
$var reg 1 A q_internal $end
$upscope $end
$upscope $end
$scope module gen_ff(5) $end
$scope module ff $end
$var reg 1 B d $end
$var reg 1 C clk $end
$var reg 1 D q $end
$var reg 1 E q_n $end
$var reg 1 F q_internal $end
$upscope $end
$upscope $end
$scope module gen_ff(6) $end
$scope module ff $end
$var reg 1 G d $end
$var reg 1 H clk $end
$var reg 1 I q $end
$var reg 1 J q_n $end
$var reg 1 K q_internal $end
$upscope $end
$upscope $end
$scope module gen_ff(7) $end
$scope module ff $end
$var reg 1 L d $end
$var reg 1 M clk $end
$var reg 1 N q $end
$var reg 1 O q_n $end
$var reg 1 P q_internal $end
$upscope $end
$upscope $end
$upscope $end
$upscope $end
$enddefinitions $end
#0
b00000000 !
0"
b00000000 #
b11111111 $
b00000000 %
0&
b00000000 '
b11111111 (
0)
0*
0+
1,
0-
0.
0/
00
11
02
03
04
05
16
07
08
09
0:
1;
0<
0=
0>
0?
1@
0A
0B
0C
0D
1E
0F
0G
0H
0I
1J
0K
0L
0M
0N
1O
0P
#5000000
1"
1&
1*
1/
14
19
1>
1C
1H
1M
#10000000
b11111111 !
0"
b11111111 %
0&
1)
0*
1.
0/
13
04
18
09
1=
0>
1B
0C
1G
0H
1L
0M
#15000000
1"
b11111111 #
b00000000 $
1&
b11111111 '
b00000000 (
1*
1+
0,
1-
1/
10
01
12
14
15
06
17
19
1:
0;
1<
1>
1?
0@
1A
1C
1D
0E
1F
1H
1I
0J
1K
1M
1N
0O
1P
#20000000
b10101010 !
0"
b10101010 %
0&
0)
0*
0/
03
04
09
0=
0>
0C
0G
0H
0M
#25000000
1"
b10101010 #
b01010101 $
1&
b10101010 '
b01010101 (
1*
0+
1,
0-
1/
14
05
16
07
19
1>
0?
1@
0A
1C
1H
0I
1J
0K
1M
#30000000
b01010101 !
0"
b01010101 %
0&
1)
0*
0.
0/
13
04
08
09
1=
0>
0B
0C
1G
0H
0L
0M
#35000000
1"
b01010101 #
b10101010 $
1&
b01010101 '
b10101010 (
1*
1+
0,
1-
1/
00
11
02
14
15
06
17
19
0:
1;
0<
1>
1?
0@
1A
1C
0D
1E
0F
1H
1I
0J
1K
1M
0N
1O
0P
#40000000
b11001100 !
0"
b11001100 %
0&
0)
0*
0/
04
18
09
0=
0>
0C
0H
1L
0M
#45000000
1"
b11001100 #
b00110011 $
1&
b11001100 '
b00110011 (
1*
0+
1,
0-
1/
14
19
1:
0;
1<
1>
0?
1@
0A
1C
1H
1M
1N
0O
1P
#50000000
b00110011 !
0"
b00110011 %
0&
1)
0*
1.
0/
03
04
08
09
1=
0>
1B
0C
0G
0H
0L
0M
#55000000
1"
b00110011 #
b11001100 $
1&
b00110011 '
b11001100 (
1*
1+
0,
1-
1/
10
01
12
14
05
16
07
19
0:
1;
0<
1>
1?
0@
1A
1C
1D
0E
1F
1H
0I
1J
0K
1M
0N
1O
0P
#60000000
b11110000 !
0"
b11110000 %
0&
0)
0*
0.
0/
04
09
0>
0C
1G
0H
1L
0M
#65000000
1"
b11110000 #
b00001111 $
1&
b11110000 '
b00001111 (
1*
0+
1,
0-
1/
00
11
02
14
19
1>
1C
1H
1I
0J
1K
1M
1N
0O
1P
#70000000
b00001111 !
0"
b00001111 %
0&
1)
0*
1.
0/
13
04
18
09
0=
0>
0B
0C
0G
0H
0L
0M
#75000000
1"
b00001111 #
b11110000 $
1&
b00001111 '
b11110000 (
1*
1+
0,
1-
1/
10
01
12
14
15
06
17
19
1:
0;
1<
1>
0?
1@
0A
1C
0D
1E
0F
1H
0I
1J
0K
1M
0N
1O
0P
