Aula03092025/Projetos_Shift_Register_SIPO/shift_register_sipo.vhd
-- Shift Register SIPO 8-bits
-- Baseado em: Starting Electronics VHDL Tutorial
library IEEE;
use IEEE.STD_LOGIC_1164.ALL;

entity shift_register_sipo is
    port(
        CLK        : in  STD_LOGIC;
        RESET      : in  STD_LOGIC;
        SERIAL_IN  : in  STD_LOGIC;
        PARALLEL_OUT : out STD_LOGIC_VECTOR(7 downto 0)
    );
end shift_register_sipo;

architecture Behavioral of shift_register_sipo is
    signal shift_reg : STD_LOGIC_VECTOR(7 downto 0) := "00000000";
begin
    process(CLK, RESET)
    begin
        if RESET = '1' then
            shift_reg <= "00000000";
        elsif rising_edge(CLK) then
            -- Desloca à direita, novo bit entra pela esquerda
            shift_reg <= SERIAL_IN & shift_reg(7 downto 1);
        end if;
    end process;
    
    PARALLEL_OUT <= shift_reg;
end Behavioral;

Aula03092025/Projetos_Shift_Register_SIPO/tb_shift_sipo_2.vhd
library IEEE;
use IEEE.STD_LOGIC_1164.ALL;

entity tb_shift_sipo is
end tb_shift_sipo;

architecture Behavioral of tb_shift_sipo is
    component shift_register_sipo
        port(
            CLK          : in  STD_LOGIC;
            RESET        : in  STD_LOGIC;
            SERIAL_IN    : in  STD_LOGIC;
            PARALLEL_OUT : out STD_LOGIC_VECTOR(7 downto 0)
        );
    end component;

    -- Sinais para observação no GTKWave
    signal CLK_tb           : STD_LOGIC := '0';
    signal RESET_tb         : STD_LOGIC;
    signal SERIAL_IN_tb     : STD_LOGIC;
    signal PARALLEL_OUT_tb  : STD_LOGIC_VECTOR(7 downto 0);

    -- Alias para bits individuais (para facilitar visualização)
    signal BIT7 : STD_LOGIC;
    signal BIT6 : STD_LOGIC;
    signal BIT5 : STD_LOGIC;
    signal BIT4 : STD_LOGIC;
    signal BIT3 : STD_LOGIC;
    signal BIT2 : STD_LOGIC;
    signal BIT1 : STD_LOGIC;
    signal BIT0 : STD_LOGIC;

    constant clock_period : time := 10 ns;

    type bit_array is array (0 to 7) of STD_LOGIC;
    signal test_sequence : bit_array := ('1','0','1','1','0','1','0','1');

begin
    -- Instância do DUT
    uut: shift_register_sipo port map (
        CLK => CLK_tb,
        RESET => RESET_tb,
        SERIAL_IN => SERIAL_IN_tb,
        PARALLEL_OUT => PARALLEL_OUT_tb
    );

    -- Mapear bits individuais
    BIT7 <= PARALLEL_OUT_tb(7);
    BIT6 <= PARALLEL_OUT_tb(6);
    BIT5 <= PARALLEL_OUT_tb(5);
    BIT4 <= PARALLEL_OUT_tb(4);
    BIT3 <= PARALLEL_OUT_tb(3);
    BIT2 <= PARALLEL_OUT_tb(2);
    BIT1 <= PARALLEL_OUT_tb(1);
    BIT0 <= PARALLEL_OUT_tb(0);

    -- Geração do clock
    clock_process: process
    begin
        while true loop
            CLK_tb <= '0';
            wait for clock_period/2;
            CLK_tb <= '1';
            wait for clock_period/2;
        end loop;
    end process;

    -- Processo de estímulos
    stim_proc: process
    begin
        RESET_tb <= '1';
        SERIAL_IN_tb <= '0';
        wait for 20 ns;

        RESET_tb <= '0';
        wait for 10 ns;

        for i in 0 to 7 loop
            SERIAL_IN_tb <= test_sequence(i);
            wait for clock_period;
        end loop;

        SERIAL_IN_tb <= '0';
        wait for 50 ns;

        wait;
    end process;

end Behavioral;

Aula03092025/Projetos_Shift_Register_SIPO/shift_sipo.vcd
$date
  Tue Aug 05 17:51:57 2025
$end
$version
  GHDL v0
$end
$timescale
  1 fs
$end
$scope module standard $end
$upscope $end
$scope module std_logic_1164 $end
$upscope $end
$scope module tb_shift_sipo $end
$var reg 1 ! clk_tb $end
$var reg 1 " reset_tb $end
$var reg 1 # serial_in_tb $end
$var reg 8 $ parallel_out_tb[7:0] $end
$var reg 8 % test_sequence[0:7] $end
$scope module uut $end
$var reg 1 & clk $end
$var reg 1 ' reset $end
$var reg 1 ( serial_in $end
$var reg 8 ) parallel_out[7:0] $end
$var reg 8 * shift_reg[7:0] $end
$upscope $end
$upscope $end
$enddefinitions $end
#0
0!
1"
0#
b00000000 $
b10110101 %
0&
1'
0(
b00000000 )
b00000000 *
#5000000
1!
1&
#10000000
0!
0&
#15000000
1!
1&
#20000000
0!
0"
0&
0'
#25000000
1!
1&
#30000000
0!
1#
0&
1(
#35000000
1!
b10000000 $
1&
b10000000 )
b10000000 *
#40000000
0!
0#
0&
0(
#45000000
1!
b01000000 $
1&
b01000000 )
b01000000 *
#50000000
0!
1#
0&
1(
#55000000
1!
b10100000 $
1&
b10100000 )
b10100000 *
#60000000
0!
0&
#65000000
1!
b11010000 $
1&
b11010000 )
b11010000 *
#70000000
0!
0#
0&
0(
#75000000
1!
b01101000 $
1&
b01101000 )
b01101000 *
#80000000
0!
1#
0&
1(
#85000000
1!
b10110100 $
1&
b10110100 )
b10110100 *
#90000000
0!
0#
0&
0(
#95000000
1!
b01011010 $
1&
b01011010 )
b01011010 *
#100000000
0!
1#
0&
1(
#105000000
1!
b10101101 $
1&
b10101101 )
b10101101 *
#110000000
0!
0#
0&
0(
#115000000
1!
b01010110 $
1&
b01010110 )
b01010110 *
#120000000
0!
0&
#125000000
1!
b00101011 $
1&
b00101011 )
b00101011 *
#130000000
0!
0&
#135000000
1!
b00010101 $
1&
b00010101 )
b00010101 *
#140000000
0!
0&
#145000000
1!
b00001010 $
1&
b00001010 )
b00001010 *
#150000000
0!
0&
#155000000
1!
b00000101 $
1&
b00000101 )
b00000101 *
#160000000
0!
0&
#165000000
1!
b00000010 $
1&
b00000010 )
b00000010 *
#170000000
0!
0&
#175000000
1!
b00000001 $
1&
b00000001 )
b00000001 *
#180000000
0!
0&
#185000000
1!
b00000000 $
1&
b00000000 )
b00000000 *
