Aula03092025/Projetos_PisoCircular/piso.vhd
library ieee;
use ieee.std_logic_1164.all;

entity piso is
    port (
        Clk         : in  std_logic;
        reset       : in  std_logic;                      -- Reset assíncrono (ativa alto)
        parallel_in : in  std_logic_vector(3 downto 0);
        load        : in  std_logic;
        shift       : in  std_logic;
        serial_out  : out std_logic;

        -- Sinais internos visíveis externamente
        q0, q1, q2, q3 : out std_logic
    );
end entity;


architecture behavioral of piso is
    signal load_value : std_logic_vector(3 downto 0) := "0000";
begin

    process(Clk, reset)
    begin
        if reset = '1' then
            load_value <= (others => '0');
            serial_out <= '0';
        elsif rising_edge(Clk) then
            if load = '1' then
                load_value <= parallel_in;
            elsif shift = '1' then
                serial_out <= load_value(3);
                load_value(3) <= load_value(2);
                load_value(2) <= load_value(1);
                load_value(1) <= load_value(0);
                load_value(0) <= load_value(3); -- realimentação circular
            end if;
        end if;
    end process;

    -- Conexão dos bits internos às saídas
    q3 <= load_value(3);
    q2 <= load_value(2);
    q1 <= load_value(1);
    q0 <= load_value(0);

end behavioral;

Aula03092025/Projetos_PisoCircular/tb_piso_shift.vhd
library ieee;
use ieee.std_logic_1164.all;

entity tb_piso_shift is
end entity;

architecture sim of tb_piso_shift is
  -- Sinais principais
  signal Clk         : std_logic := '0';
  signal reset       : std_logic := '0';
  signal load        : std_logic := '0';
  signal shift       : std_logic := '0';
  signal parallel_in : std_logic_vector(3 downto 0) := (others => '0');
  signal serial_out  : std_logic;

  -- Sinais internos (bits individuais do registrador)
  signal q0, q1, q2, q3 : std_logic;

  component piso
    port (
      Clk         : in  std_logic;
      reset       : in  std_logic;
      parallel_in : in  std_logic_vector(3 downto 0);
      load        : in  std_logic;
      shift       : in  std_logic;
      serial_out  : out std_logic;
      q0, q1, q2, q3 : out std_logic
    );
  end component;

begin

  -- Instância do componente PISO
  uut: piso port map(
    Clk         => Clk,
    reset       => reset,
    parallel_in => parallel_in,
    load        => load,
    shift       => shift,
    serial_out  => serial_out,
    q0 => q0, q1 => q1, q2 => q2, q3 => q3
  );

  -- Geração de clock: 10 ns (50 MHz)
  clk_process: process
  begin
    while now < 300 ns loop
      Clk <= not Clk;
      wait for 5 ns;
    end loop;
    wait;
  end process;

  -- Estímulos para teste
  stim_proc: process
  begin
    -- Reset global
    reset <= '1';
    wait for 10 ns;
    reset <= '0';

    wait for 10 ns;

    -- Carrega o valor paralelo: 1011
    parallel_in <= "1011"; -- q3=1, q2=0, q1=1, q0=1
    load <= '1';
    shift <= '0';
    wait for 10 ns;

    -- Finaliza carga
    load <= '0';
    wait for 10 ns;

    -- Habilita deslocamento circular por 10 ciclos (~100 ns)
    shift <= '1';
    wait for 250 ns;

    -- Desativa deslocamento
    shift <= '0';
    wait;

  end process;

end architecture;

Aula03092025/Projetos_PisoCircular/piso.vcd
$date
  Tue Aug 05 16:25:38 2025
$end
$version
  GHDL v0
$end
$timescale
  1 fs
$end
$scope module standard $end
$upscope $end
$scope module std_logic_1164 $end
$upscope $end
$scope module tb_piso_shift $end
$var reg 1 ! clk $end
$var reg 1 " reset $end
$var reg 1 # load $end
$var reg 1 $ shift $end
$var reg 4 % parallel_in[3:0] $end
$var reg 1 & serial_out $end
$var reg 1 ' q0 $end
$var reg 1 ( q1 $end
$var reg 1 ) q2 $end
$var reg 1 * q3 $end
$scope module uut $end
$var reg 1 + clk $end
$var reg 1 , reset $end
$var reg 4 - parallel_in[3:0] $end
$var reg 1 . load $end
$var reg 1 / shift $end
$var reg 1 0 serial_out $end
$var reg 1 1 q0 $end
$var reg 1 2 q1 $end
$var reg 1 3 q2 $end
$var reg 1 4 q3 $end
$var reg 4 5 load_value[3:0] $end
$upscope $end
$upscope $end
$enddefinitions $end
#0
1!
1"
0#
0$
b0000 %
0&
0'
0(
0)
0*
1+
1,
b0000 -
0.
0/
00
01
02
03
04
b0000 5
#5000000
0!
0+
#10000000
1!
0"
1+
0,
#15000000
0!
0+
#20000000
1!
1#
b1011 %
1'
1(
1*
1+
b1011 -
1.
11
12
14
b1011 5
#25000000
0!
0+
#30000000
1!
0#
1+
0.
#35000000
0!
0+
#40000000
1!
1$
1&
1)
0*
1+
1/
10
13
04
b0111 5
#45000000
0!
0+
#50000000
1!
0&
0'
1*
1+
00
01
14
b1110 5
#55000000
0!
0+
#60000000
1!
1&
1'
0(
1+
10
11
02
b1101 5
#65000000
0!
0+
#70000000
1!
1(
0)
1+
12
03
b1011 5
#75000000
0!
0+
#80000000
1!
1)
0*
1+
13
04
b0111 5
#85000000
0!
0+
#90000000
1!
0&
0'
1*
1+
00
01
14
b1110 5
#95000000
0!
0+
#100000000
1!
1&
1'
0(
1+
10
11
02
b1101 5
#105000000
0!
0+
#110000000
1!
1(
0)
1+
12
03
b1011 5
#115000000
0!
0+
#120000000
1!
1)
0*
1+
13
04
b0111 5
#125000000
0!
0+
#130000000
1!
0&
0'
1*
1+
00
01
14
b1110 5
#135000000
0!
0+
#140000000
1!
1&
1'
0(
1+
10
11
02
b1101 5
#145000000
0!
0+
#150000000
1!
1(
0)
1+
12
03
b1011 5
#155000000
0!
0+
#160000000
1!
1)
0*
1+
13
04
b0111 5
#165000000
0!
0+
#170000000
1!
0&
0'
1*
1+
00
01
14
b1110 5
#175000000
0!
0+
#180000000
1!
1&
1'
0(
1+
10
11
02
b1101 5
#185000000
0!
0+
#190000000
1!
1(
0)
1+
12
03
b1011 5
#195000000
0!
0+
#200000000
1!
1)
0*
1+
13
04
b0111 5
#205000000
0!
0+
#210000000
1!
0&
0'
1*
1+
00
01
14
b1110 5
#215000000
0!
0+
#220000000
1!
1&
1'
0(
1+
10
11
02
b1101 5
#225000000
0!
0+
#230000000
1!
1(
0)
1+
12
03
b1011 5
#235000000
0!
0+
#240000000
1!
1)
0*
1+
13
04
b0111 5
#245000000
0!
0+
#250000000
1!
0&
0'
1*
1+
00
01
14
b1110 5
#255000000
0!
0+
#260000000
1!
1&
1'
0(
1+
10
11
02
b1101 5
#265000000
0!
0+
#270000000
1!
1(
0)
1+
12
03
b1011 5
#275000000
0!
0+
#280000000
1!
1)
0*
1+
13
04
b0111 5
#285000000
0!
0+
#290000000
1!
0$
1+
0/
