Aula03092025/Projetos_Updown_Counter/updown_counter.vhd
-- Contador Up-Down 4-bits
library IEEE;
use IEEE.STD_LOGIC_1164.ALL;
use IEEE.NUMERIC_STD.ALL;

entity updown_counter is
    port(
        clk     : in  STD_LOGIC;
        reset   : in  STD_LOGIC;
        up_down : in  STD_LOGIC;  -- '1' para down, '0' para up
        counter : out STD_LOGIC_VECTOR(3 downto 0)
    );
end updown_counter;

architecture Behavioral of updown_counter is
    signal counter_updown : unsigned(3 downto 0);
begin
    process(clk)
    begin
        if rising_edge(clk) then
            if reset = '1' then
                counter_updown <= (others => '0');
            elsif up_down = '1' then
                counter_updown <= counter_updown - 1;  -- count down
            else
                counter_updown <= counter_updown + 1;  -- count up
            end if;
        end if;
    end process;
    
    counter <= std_logic_vector(counter_updown); -- conversão para saída
end Behavioral;

Aula03092025/Projetos_Updown_Counter/tb_updown_counter.vhd
-- Testbench para Contador Up-Down
library IEEE;
use IEEE.STD_LOGIC_1164.ALL;

entity tb_updown_counter is
end tb_updown_counter;

architecture Behavioral of tb_updown_counter is
    component updown_counter
        port(
            clk     : in  STD_LOGIC;
            reset   : in  STD_LOGIC;
            up_down : in  STD_LOGIC;
            counter : out STD_LOGIC_VECTOR(3 downto 0)
        );
    end component;
    
    signal clk_tb     : STD_LOGIC := '0';
    signal reset_tb   : STD_LOGIC;
    signal up_down_tb : STD_LOGIC;
    signal counter_tb : STD_LOGIC_VECTOR(3 downto 0);
    
    constant clock_period : time := 10 ns;
    
begin
    uut: updown_counter port map (
        clk => clk_tb,
        reset => reset_tb,
        up_down => up_down_tb,
        counter => counter_tb
    );
    
    clock_process: process
    begin
        clk_tb <= '0';
        wait for clock_period/2;
        clk_tb <= '1';
        wait for clock_period/2;
    end process;
    
    stim_proc: process
    begin
        -- Reset inicial
        reset_tb <= '1';
        up_down_tb <= '0';
        wait for 20 ns;
        
        reset_tb <= '0';
        wait for 10 ns;
        
        -- Conta para cima
        up_down_tb <= '0';
        wait for 200 ns;  -- 20 ciclos
        
        -- Conta para baixo
        up_down_tb <= '1';
        wait for 300 ns;  -- 30 ciclos
        
        -- Teste de reset durante operação
        reset_tb <= '1';
        wait for 20 ns;
        reset_tb <= '0';
        
        -- Continua contando para cima
        up_down_tb <= '0';
        wait for 100 ns;
        
        wait;
    end process;
end Behavioral;

Aula03092025/Projetos_Updown_Counter/updown_counter.vcd
$date
  Tue Aug 05 19:48:21 2025
$end
$version
  GHDL v0
$end
$timescale
  1 fs
$end
$scope module standard $end
$upscope $end
$scope module std_logic_1164 $end
$upscope $end
$scope module numeric_std $end
$upscope $end
$scope module tb_updown_counter $end
$var reg 1 ! clk_tb $end
$var reg 1 " reset_tb $end
$var reg 1 # up_down_tb $end
$var reg 4 $ counter_tb[3:0] $end
$scope module uut $end
$var reg 1 % clk $end
$var reg 1 & reset $end
$var reg 1 ' up_down $end
$var reg 4 ( counter[3:0] $end
$var reg 4 ) counter_updown[3:0] $end
$upscope $end
$upscope $end
$enddefinitions $end
#0
0!
1"
0#
bUUUU $
0%
1&
0'
bUUUU (
bUUUU )
#5000000
1!
b0000 $
1%
b0000 (
b0000 )
#10000000
0!
0%
#15000000
1!
1%
#20000000
0!
0"
0%
0&
#25000000
1!
b0001 $
1%
b0001 (
b0001 )
#30000000
0!
0%
#35000000
1!
b0010 $
1%
b0010 (
b0010 )
#40000000
0!
0%
#45000000
1!
b0011 $
1%
b0011 (
b0011 )
#50000000
0!
0%
#55000000
1!
b0100 $
1%
b0100 (
b0100 )
#60000000
0!
0%
#65000000
1!
b0101 $
1%
b0101 (
b0101 )
#70000000
0!
0%
#75000000
1!
b0110 $
1%
b0110 (
b0110 )
#80000000
0!
0%
#85000000
1!
b0111 $
1%
b0111 (
b0111 )
#90000000
0!
0%
#95000000
1!
b1000 $
1%
b1000 (
b1000 )
#100000000
0!
0%
#105000000
1!
b1001 $
1%
b1001 (
b1001 )
#110000000
0!
0%
#115000000
1!
b1010 $
1%
b1010 (
b1010 )
#120000000
0!
0%
#125000000
1!
b1011 $
1%
b1011 (
b1011 )
#130000000
0!
0%
#135000000
1!
b1100 $
1%
b1100 (
b1100 )
#140000000
0!
0%
#145000000
1!
b1101 $
1%
b1101 (
b1101 )
#150000000
0!
0%
#155000000
1!
b1110 $
1%
b1110 (
b1110 )
#160000000
0!
0%
#165000000
1!
b1111 $
1%
b1111 (
b1111 )
#170000000
0!
0%
#175000000
1!
b0000 $
1%
b0000 (
b0000 )
#180000000
0!
0%
#185000000
1!
b0001 $
1%
b0001 (
b0001 )
#190000000
0!
0%
#195000000
1!
b0010 $
1%
b0010 (
b0010 )
