Aula03092025/Projetos_PISO/piso.vhd
library ieee;
use ieee.std_logic_1164.all;

entity piso is
    port (
        Clk         : in  std_logic;                      -- Clock
        parallel_in : in  std_logic_vector(3 downto 0);   -- Dados de entrada paralela
        load        : in  std_logic;                      -- Carregamento paralelo (ativa alto)
        shift       : in  std_logic;                      -- Habilita deslocamento serial (ativa alto)
        serial_out  : out std_logic                       -- Saída serial
    );
end piso;

architecture behavioral of piso is
    signal load_value : std_logic_vector(3 downto 0) := "0000";
begin

    process(Clk)
    begin
        if rising_edge(Clk) then
            if load = '1' then
                -- Carregamento paralelo
                load_value <= parallel_in;
            elsif shift = '1' then
                -- Deslocamento somente se habilitado
                serial_out <= load_value(3);              -- MSB na saída
                load_value(3) <= load_value(2);
                load_value(2) <= load_value(1);
                load_value(1) <= load_value(0);
                load_value(0) <= '0';                    -- LSB limpo
            end if;
            -- Caso contrário: mantém os valores
        end if;
    end process;

end behavioral;

Aula03092025/Projetos_PISO/tb_piso_shift.vhd
library ieee;
use ieee.std_logic_1164.all;

entity tb_piso_shift is
end entity;

architecture sim of tb_piso_shift is
  signal Clk         : std_logic := '0';
  signal load        : std_logic := '0';
  signal shift       : std_logic := '0';
  signal parallel_in : std_logic_vector(3 downto 0) := (others => '0');
  signal serial_out  : std_logic;

  component piso
    port (
      Clk         : in  std_logic;
      parallel_in : in  std_logic_vector(3 downto 0);
      load        : in  std_logic;
      shift       : in  std_logic;
      serial_out  : out std_logic
    );
  end component;

begin

  uut: piso port map(
    Clk         => Clk,
    parallel_in => parallel_in,
    load        => load,
    shift       => shift,
    serial_out  => serial_out
  );

  -- Clock de 10 ns
  clk_process: process
  begin
    while now < 200 ns loop
      Clk <= not Clk;
      wait for 5 ns;
    end loop;
    wait;
  end process;

  -- Estímulos
  stim_proc: process
  begin
    -- Espera inicial
    wait for 10 ns;

    -- Carga paralela
    parallel_in <= "1011"; -- d(3)=1, d(2)=0, d(1)=1, d(0)=1
    load <= '1';
    shift <= '0';
    wait for 10 ns;

    load <= '0';
    wait for 10 ns;

    -- Deslocamento serial habilitado
    shift <= '1';
    for i in 0 to 3 loop
      wait for 10 ns;
    end loop;

    -- Finaliza
    shift <= '0';
    wait;
  end process;

end architecture;

Aula03092025/Projetos_PISO/piso_shift.vcd
$date
  Wed Sep 03 10:39:02 2025
$end
$version
  GHDL v0
$end
$timescale
  1 fs
$end
$scope module standard $end
$upscope $end
$scope module std_logic_1164 $end
$upscope $end
$scope module tb_piso_shift $end
$var reg 1 ! clk $end
$var reg 1 " load $end
$var reg 1 # shift $end
$var reg 4 $ parallel_in[3:0] $end
$var reg 1 % serial_out $end
$scope module uut $end
$var reg 1 & clk $end
$var reg 4 ' parallel_in[3:0] $end
$var reg 1 ( load $end
$var reg 1 ) shift $end
$var reg 1 * serial_out $end
$var reg 4 + load_value[3:0] $end
$upscope $end
$upscope $end
$enddefinitions $end
#0
1!
0"
0#
b0000 $
U%
1&
b0000 '
0(
0)
U*
b0000 +
#5000000
0!
0&
#10000000
1!
1"
b1011 $
1&
b1011 '
1(
b1011 +
#15000000
0!
0&
#20000000
1!
0"
1&
0(
#25000000
0!
0&
#30000000
1!
1#
1%
1&
1)
1*
b0110 +
#35000000
0!
0&
#40000000
1!
0%
1&
0*
b1100 +
#45000000
0!
0&
#50000000
1!
1%
1&
1*
b1000 +
#55000000
0!
0&
#60000000
1!
1&
b0000 +
#65000000
0!
0&
#70000000
1!
0#
1&
0)
